memetext/__init__.py
memetext/memetext.py
memetext-0.1.2.dist-info/entry_points.txt
memetext-0.1.2.dist-info/WHEEL
memetext-0.1.2.dist-info/METADATA
memetext-0.1.2.dist-info/RECORD
