Metadata-Version: 2.1
Name: memetext
Version: 0.1.2
Summary: Write top and bottom text on an image, block meme style.
Author: Ryan Townshend
Author-email: citizen.townshend@gmail.com
Requires-Python: >=3.8,<4.0
Classifier: Programming Language :: Python :: 3
Classifier: Programming Language :: Python :: 3.10
Classifier: Programming Language :: Python :: 3.8
Classifier: Programming Language :: Python :: 3.9
Requires-Dist: Pillow (>=8.2.0,<9.0.0)
Requires-Dist: click (>=8.0.3,<9.0.0)
